Workbook

Sheet MASTER MEMBERS
A1: Lead_ID | B1: Record_Status | C1: Freight_Relevant | D1: Data_Source | E1: Assigned_Rep | F1: Last_Updated | G1: Updated_By | H1: Company_Name | I1: Website | J1: Industry | K1: Sub_Industry | L1: HQ_State | M1: Employees | N1: Annual_Revenue | O1: PE_Sponsor | P1: Portfolio_Company | Q1: CT_TTM_Spend | R1: Contact_First | S1: Contact_Last | T1: Contact_Title | U1: Contact_Email | V1: Contact_Phone | W1: Est_Freight_Spend | X1: Confirmed_Freight_Spend | Y1: TMS_In_Use | Z1: Tech_State | AA1: Under_Contract | AB1: Contract_Status | AC1: Capacity_Source | AD1: Private_Fleet | AE1: Lane_Data_Available | AF1: Freight_Opportunity | AG1: Engrainment | AH1: Freight_Intensity | AI1: Actionability | AJ1: Warmth | AK1: Fit_v3_Score | AL1: Fit_Tier | AM1: Spend_Bucket | AN1: Priority | AO1: Suggested_Supplier | AP1: Service_Fit | AQ1: Quality_Strategic | AR1: Qualified | AS1: Notes
A2: CT-00001 | B2: Ready to Call | C2: Yes | D2: Freight Analysis + SFDC | H2: American Tire Distributors | I2: atd.com | J2: Distribution | K2: Auto Parts | L2: NC | M2: 5000 | N2: 5300000000 | O2: TPG | P2: Yes | Q2: 11464766 | R2: Alex | S2: Keyer | T2: SVP Supply Chain & Ops | U2: akeyer@atd.com | V2: +1 704-632-7110 | W2: 291500000 | AF2: 89.3 | AG2: 99.3 | AH2: 90 | AI2: 100 | AJ2: 100 | AK2: 95.1 | AL2: A | AM2: $10M+ | AN2: HOT | AO2: GEODIS | AP2: LTL, FTL, Brokerage | AQ2: Yes
A3: CT-00002 | B3: Ready to Call | C3: Yes | D3: Freight Analysis + SFDC | H3: Solenis LLC | I3: solenis.com | J3: Manufacturing | K3: Chemicals | L3: DE | M3: 15400 | N3: 3468524000 | O3: Platinum Equity | P3: Yes | Q3: 3101083 | R3: Sheila | S3: Tiegs | T3: VP Supply Chain Americas | U3: stiegs@solenis.com | W3: 208111440 | AF3: 86.4 | AG3: 93.7 | AH3: 92 | AI3: 100 | AJ3: 100 | AK3: 92.8 | AL3: A | AM3: $10M+ | AN3: HOT | AO3: GEODIS | AP3: LTL, FTL, Brokerage | AQ3: Yes
A4: CT-00003 | B4: Ready to Call | C4: Yes | D4: Freight Analysis + SFDC | H4: BlueTriton Brands | I4: bluetriton.com | J4: Consumer Products | K4: Beverage | L4: CT | M4: 7000 | N4: 4500000000 | O4: One Rock Capital | P4: Yes | Q4: 620000 | R4: Robert | S4: Austin | T4: VP Logistics | U4: raustin@bluetriton.com | W4: 247500000 | AF4: 87.9 | AG4: 84.7 | AH4: 95 | AI4: 100 | AJ4: 100 | AK4: 91 | AL4: A | AM4: $10M+ | AN4: HOT | AO4: GEODIS | AP4: LTL, Retail Cross Dock, Brokerage | AQ4: Yes
A5: CT-00004 | B5: Ready to Call | C5: Yes | D5: Freight Analysis + SFDC | H5: US Foods | I5: usfoods.com | J5: Distribution | K5: Food Distribution | L5: IL | M5: 70000 | N5: 37000000000 | O5: Independent | P5: No | Q5: 480000 | R5: Andrew | S5: Iaconis | T5: VP Supply Chain | U5: aiaconis@usfoods.com | V5: +1 847-720-8000 | W5: 2956800000 | AF5: 100 | AG5: 83 | AH5: 100 | AI5: 100 | AJ5: 40 | AK5: 88.9 | AL5: A | AM5: $10M+ | AN5: HOT | AO5: GEODIS | AP5: LTL, FTL, Retail Cross Dock, Brokerage | AQ5: Yes
A6: CT-00005 | B6: Ready to Call | C6: Yes | D6: Freight Analysis + SFDC | H6: Genuine Parts Company | I6: genpt.com | J6: Distribution | K6: Auto Parts | L6: GA | M6: 60000 | N6: 23000000000 | O6: Independent | P6: No | Q6: 305000 | R6: Naveen | S6: Krishna | T6: VP Supply Chain | U6: nkrishna@genpt.com | V6: +1 678-934-5000 | W6: 1093506345 | AF6: 100 | AG6: 76.7 | AH6: 90 | AI6: 100 | AJ6: 40 | AK6: 85.5 | AL6: A | AM6: $10M+ | AN6: HOT | AO6: GEODIS | AP6: LTL, FTL, Brokerage | AQ6: Yes
A7: CT-00006 | B7: Ready to Call | C7: Yes | D7: Freight Analysis + SFDC | H7: Ecolab Inc. | I7: ecolab.com | J7: Manufacturing | K7: Chemicals | L7: MN | M7: 47000 | N7: 15000000000 | O7: Independent | P7: No | Q7: 188000 | R7: Michael | S7: Hickey | T7: SVP Supply Chain | U7: mhickey@ecolab.com | V7: +1 651-293-2233 | W7: 964872000 | AF7: 99.7 | AG7: 65.3 | AH7: 92 | AI7: 100 | AJ7: 40 | AK7: 82.3 | AL7: A | AM7: $10M+ | AN7: HOT | AO7: GEODIS | AP7: LTL, FTL, Brokerage | AQ7: Yes
A8: CT-00007 | B8: Ready to Call | C8: Yes | D8: Freight Analysis + SFDC | H8: Stryker Corporation | I8: stryker.com | J8: Manufacturing | K8: Medical Devices | L8: MI | M8: 52000 | N8: 20500000000 | O8: Independent | P8: No | Q8: 210000 | R8: Jason | S8: Beach | T8: VP Global Logistics | U8: jbeach@stryker.com | V8: +1 269-385-2600 | W8: 1381380000 | AF8: 100 | AG8: 71 | AH8: 55 | AI8: 100 | AJ8: 40 | AK8: 78.5 | AL8: A | AM8: $10M+ | AN8: HOT | AO8: GEODIS | AP8: LTL, FTL, Brokerage | AQ8: Yes
A9: CT-00008 | B9: Ready to Call | C9: Yes | D9: Freight Analysis + SFDC | H9: Berry Global | I9: berryglobal.com | J9: Manufacturing | K9: Packaging | L9: IN | M9: 40000 | N9: 13000000000 | O9: Independent | P9: No | Q9: 145000 | R9: Jason | S9: Greene | T9: Dir Distribution | U9: jgreene@berryglobal.com | W9: 780000000 | AF9: 97.8 | AG9: 56.3 | AH9: 88 | AI9: 100 | AJ9: 40 | AK9: 78.5 | AL9: A | AM9: $10M+ | AN9: HOT | AO9: GEODIS | AP9: LTL, FTL, Brokerage | AQ9: Yes
A10: CT-00009 | B10: Ready to Call | C10: Yes | D10: Freight Analysis + SFDC | H10: Parker-Hannifin | I10: parker.com | J10: Manufacturing | K10: Machinery | L10: OH | M10: 58000 | N10: 19900000000 | O10: Independent | P10: No | Q10: 95000 | R10: Roger | S10: Sherrard | T10: Dir Transportation | U10: rsherrard@parker.com | V10: +1 216-896-3000 | W10: 1191000000 | AF10: 100 | AG10: 50.7 | AH10: 88 | AI10: 100 | AJ10: 40 | AK10: 77.4 | AL10: A | AM10: $10M+ | AN10: HOT | AO10: GEODIS | AP10: LTL, FTL, Brokerage | AQ10: Yes
A11: CT-00010 | B11: Ready to Call | C11: Yes | D11: Freight Analysis + SFDC | H11: Kubota North America | I11: kubotausa.com | J11: Manufacturing | K11: Machinery | L11: TX | M11: 3200 | N11: 4200000000 | O11: Independent | P11: No | Q11: 42000 | R11: Jenny | S11: Diaz | T11: Logistics Manager | U11: jdiaz@kubota.com | W11: 84000000 | AF11: 78.5 | AG11: 39.3 | AH11: 88 | AI11: 100 | AJ11: 40 | AK11: 67.5 | AL11: B | AM11: $10M+ | AN11: HOT | AO11: GEODIS | AP11: LTL, FTL | AQ11: Yes
A12: CT-00011 | B12: Ready to Call | C12: Yes | D12: Freight Analysis + SFDC | H12: LK Packaging | I12: lkpackaging.com | J12: Wholesale | K12: Packaging | L12: TX | M12: 320 | N12: 180000000 | O12: Kohlberg & Company | P12: Yes | Q12: 95000 | R12: Marcus | S12: Lowe | T12: Ops Manager | U12: mlowe@lkpackaging.com | W12: 2100000 | AF12: 46.4 | AG12: 50.7 | AH12: 88 | AI12: 75 | AJ12: 100 | AK12: 63.6 | AL12: B | AM12: $2-5M | AN12: HOT | AO12: Redwood / GEODIS | AP12: LTL, FTL, Brokerage | AQ12: Yes
A13: CT-00012 | B13: Enriching | C13: Yes | D13: SFDC | H13: Shearer's Foods | I13: shearers.com | J13: Consumer Products | K13: Food | L13: OH | M13: 5000 | N13: 1600000000 | O13: Ontario Teachers | P13: Yes | Q13: 0 | W13: 88000000 | AF13: 78.9 | AG13: 25.3 | AH13: 98 | AI13: 0 | AJ13: 100 | AK13: 56 | AL13: B | AM13: $10M+ | AN13: WARM | AO13: GEODIS | AP13: LTL, FTL, Retail Cross Dock | AQ13: No
A14: CT-00013 | B14: Enriching | C14: Yes | D14: SFDC | H14: Champion Home Builders | I14: championhomes.com | J14: Manufacturing | K14: Building Materials | L14: MI | M14: 8500 | N14: 2100000000 | O14: Independent | P14: No | Q14: 0 | W14: 126000000 | AF14: 82 | AG14: 25.3 | AH14: 97 | AI14: 0 | AJ14: 40 | AK14: 50.8 | AL14: C | AM14: $10M+ | AN14: COLD | AO14: GEODIS | AP14: LTL, FTL | AQ14: No
A15: CT-00014 | B15: Enriching | C15: Yes | D15: SFDC | H15: Nekoosa Coated Products | I15: nekoosa.com | J15: Manufacturing | K15: Paper | L15: WI | M15: 600 | N15: 140000000 | O15: Sole Source Capital | P15: Yes | Q15: 0 | W15: 8400000 | AF15: 58.5 | AG15: 25.3 | AH15: 85 | AI15: 0 | AJ15: 100 | AK15: 47.9 | AL15: C | AM15: $5-10M | AN15: COLD | AO15: GEODIS | AP15: LTL, FTL | AQ15: No
A16: CT-00015 | B16: Enriching | C16: Yes | D16: SFDC | H16: Diversified Healthcare | I16: dhc.com | J16: Healthcare | K16: Medical Supplies | L16: MA | M16: 1200 | N16: 900000000 | O16: Independent | P16: No | Q16: 0 | W16: 18000000 | AF16: 65.1 | AG16: 25.3 | AH16: 50 | AI16: 0 | AJ16: 40 | AK16: 38.6 | AL16: D | AM16: $10M+ | AN16: COLD | AO16: GEODIS | AP16: LTL | AQ16: No

Sheet TOUCHPOINTS
A1: Lead_ID | B1: Company_Name | C1: Contact_First | D1: Contact_Last | E1: Contact_Title | F1: Contact_Email | G1: Assigned_Rep | H1: Fit_Tier | I1: Priority | J1: Spend_Bucket | K1: Suggested_Supplier | L1: Cadence_Step | M1: Total_Touches | N1: Emails_Sent | O1: Calls_Made | P1: LinkedIn_Touches | Q1: Last_Touch_Date | R1: Last_Touch_Channel | S1: Days_Since_Last | T1: Next_Touch_Due | U1: Follow_Up_Flag | V1: SLA_Status | W1: Reply_Received | X1: Meeting_Booked | Y1: Outcome | Z1: Cadence_Status | AA1: Notes
A2: CT-00001 | B2: American Tire Distributors | C2: Alex | D2: Keyer | E2: SVP Supply Chain & Ops | F2: akeyer@atd.com | G2: (rep) | H2: A | I2: HOT | J2: $10M+ | K2: GEODIS | L2: 1 | M2: 1 | N2: 1 | O2: 0 | P2: 0 | Q2: 46266 | R2: Email | S2: =IF(Q2="","",TODAY()-Q2) -> 0 | T2: =IF(Q2="","",Q2+VLOOKUP(L2,CADENCE!$A:$B,2,FALSE)) -> 0 | U2: =IF(T2="","",IF(TODAY()>=T2,"FOLLOW UP","ok")) -> 0 | V2: =IF(S2="","",IF(S2>14,"OVERDUE",IF(S2>4,"DUE SOON","ON TRACK"))) -> 0 | W2: No | X2: No | Y2: contacted | Z2: Active
A3: CT-00002 | B3: Solenis LLC | C3: Sheila | D3: Tiegs | E3: VP Supply Chain Americas | F3: stiegs@solenis.com | G3: (rep) | H3: A | I3: HOT | J3: $10M+ | K3: GEODIS | L3: 2 | M3: 2 | N3: 2 | O3: 1 | P3: 1 | Q3: 46264 | R3: Call | S3: =IF(Q3="","",TODAY()-Q3) -> 0 | T3: =IF(Q3="","",Q3+VLOOKUP(L3,CADENCE!$A:$B,2,FALSE)) -> 0 | U3: =IF(T3="","",IF(TODAY()>=T3,"FOLLOW UP","ok")) -> 0 | V3: =IF(S3="","",IF(S3>14,"OVERDUE",IF(S3>4,"DUE SOON","ON TRACK"))) -> 0 | W3: No | X3: No | Y3: contacted | Z3: Active
A4: CT-00003 | B4: BlueTriton Brands | C4: Robert | D4: Austin | E4: VP Logistics | F4: raustin@bluetriton.com | G4: (rep) | H4: A | I4: HOT | J4: $10M+ | K4: GEODIS | L4: 2 | M4: 2 | N4: 3 | O4: 0 | P4: 0 | Q4: 46263 | R4: Email | S4: =IF(Q4="","",TODAY()-Q4) -> 0 | T4: =IF(Q4="","",Q4+VLOOKUP(L4,CADENCE!$A:$B,2,FALSE)) -> 0 | U4: =IF(T4="","",IF(TODAY()>=T4,"FOLLOW UP","ok")) -> 0 | V4: =IF(S4="","",IF(S4>14,"OVERDUE",IF(S4>4,"DUE SOON","ON TRACK"))) -> 0 | W4: No | X4: No | Y4: contacted | Z4: Active
A5: CT-00004 | B5: US Foods | C5: Andrew | D5: Iaconis | E5: VP Supply Chain | F5: aiaconis@usfoods.com | G5: (rep) | H5: A | I5: HOT | J5: $10M+ | K5: GEODIS | L5: 3 | M5: 3 | N5: 1 | O5: 1 | P5: 1 | Q5: 46261 | R5: LinkedIn | S5: =IF(Q5="","",TODAY()-Q5) -> 0 | T5: =IF(Q5="","",Q5+VLOOKUP(L5,CADENCE!$A:$B,2,FALSE)) -> 0 | U5: =IF(T5="","",IF(TODAY()>=T5,"FOLLOW UP","ok")) -> 0 | V5: =IF(S5="","",IF(S5>14,"OVERDUE",IF(S5>4,"DUE SOON","ON TRACK"))) -> 0 | W5: No | X5: No | Y5: contacted | Z5: Active
A6: CT-00005 | B6: Genuine Parts Company | C6: Naveen | D6: Krishna | E6: VP Supply Chain | F6: nkrishna@genpt.com | G6: (rep) | H6: A | I6: HOT | J6: $10M+ | K6: GEODIS | L6: 4 | M6: 4 | N6: 2 | O6: 0 | P6: 0 | Q6: 46259 | R6: Call | S6: =IF(Q6="","",TODAY()-Q6) -> 0 | T6: =IF(Q6="","",Q6+VLOOKUP(L6,CADENCE!$A:$B,2,FALSE)) -> 0 | U6: =IF(T6="","",IF(TODAY()>=T6,"FOLLOW UP","ok")) -> 0 | V6: =IF(S6="","",IF(S6>14,"OVERDUE",IF(S6>4,"DUE SOON","ON TRACK"))) -> 0 | W6: No | X6: No | Y6: contacted | Z6: Active
A7: CT-00006 | B7: Ecolab Inc. | C7: Michael | D7: Hickey | E7: SVP Supply Chain | F7: mhickey@ecolab.com | G7: (rep) | H7: A | I7: HOT | J7: $10M+ | K7: GEODIS | L7: 1 | M7: 1 | N7: 3 | O7: 1 | P7: 1 | Q7: 46265 | R7: Email | S7: =IF(Q7="","",TODAY()-Q7) -> 0 | T7: =IF(Q7="","",Q7+VLOOKUP(L7,CADENCE!$A:$B,2,FALSE)) -> 0 | U7: =IF(T7="","",IF(TODAY()>=T7,"FOLLOW UP","ok")) -> 0 | V7: =IF(S7="","",IF(S7>14,"OVERDUE",IF(S7>4,"DUE SOON","ON TRACK"))) -> 0 | W7: No | X7: No | Y7: contacted | Z7: Active
A8: CT-00007 | B8: Stryker Corporation | C8: Jason | D8: Beach | E8: VP Global Logistics | F8: jbeach@stryker.com | G8: (rep) | H8: A | I8: HOT | J8: $10M+ | K8: GEODIS | L8: 3 | M8: 3 | N8: 1 | O8: 0 | P8: 0 | Q8: 46262 | R8: Call | S8: =IF(Q8="","",TODAY()-Q8) -> 0 | T8: =IF(Q8="","",Q8+VLOOKUP(L8,CADENCE!$A:$B,2,FALSE)) -> 0 | U8: =IF(T8="","",IF(TODAY()>=T8,"FOLLOW UP","ok")) -> 0 | V8: =IF(S8="","",IF(S8>14,"OVERDUE",IF(S8>4,"DUE SOON","ON TRACK"))) -> 0 | W8: No | X8: No | Y8: contacted | Z8: Active
A9: CT-00008 | B9: Berry Global | C9: Jason | D9: Greene | E9: Dir Distribution | F9: jgreene@berryglobal.com | G9: (rep) | H9: A | I9: HOT | J9: $10M+ | K9: GEODIS | L9: 4 | M9: 4 | N9: 2 | O9: 1 | P9: 1 | Q9: 46260 | R9: Email | S9: =IF(Q9="","",TODAY()-Q9) -> 0 | T9: =IF(Q9="","",Q9+VLOOKUP(L9,CADENCE!$A:$B,2,FALSE)) -> 0 | U9: =IF(T9="","",IF(TODAY()>=T9,"FOLLOW UP","ok")) -> 0 | V9: =IF(S9="","",IF(S9>14,"OVERDUE",IF(S9>4,"DUE SOON","ON TRACK"))) -> 0 | W9: No | X9: No | Y9: contacted | Z9: Active
A10: CT-00009 | B10: Parker-Hannifin | C10: Roger | D10: Sherrard | E10: Dir Transportation | F10: rsherrard@parker.com | G10: (rep) | H10: A | I10: HOT | J10: $10M+ | K10: GEODIS | L10: 5 | M10: 5 | N10: 3 | O10: 0 | P10: 0 | Q10: 46258 | R10: LinkedIn | S10: =IF(Q10="","",TODAY()-Q10) -> 0 | T10: =IF(Q10="","",Q10+VLOOKUP(L10,CADENCE!$A:$B,2,FALSE)) -> 0 | U10: =IF(T10="","",IF(TODAY()>=T10,"FOLLOW UP","ok")) -> 0 | V10: =IF(S10="","",IF(S10>14,"OVERDUE",IF(S10>4,"DUE SOON","ON TRACK"))) -> 0 | W10: No | X10: No | Y10: contacted | Z10: Active
A11: CT-00010 | B11: Kubota North America | C11: Jenny | D11: Diaz | E11: Logistics Manager | F11: jdiaz@kubota.com | G11: (rep) | H11: B | I11: HOT | J11: $10M+ | K11: GEODIS | L11: 2 | M11: 2 | N11: 1 | O11: 1 | P11: 1 | Q11: 46264 | R11: Call | S11: =IF(Q11="","",TODAY()-Q11) -> 0 | T11: =IF(Q11="","",Q11+VLOOKUP(L11,CADENCE!$A:$B,2,FALSE)) -> 0 | U11: =IF(T11="","",IF(TODAY()>=T11,"FOLLOW UP","ok")) -> 0 | V11: =IF(S11="","",IF(S11>14,"OVERDUE",IF(S11>4,"DUE SOON","ON TRACK"))) -> 0 | W11: No | X11: No | Y11: contacted | Z11: Active

Sheet CADENCE
A1: Step | B1: Days_To_Next | C1: Channel
A2: 1 | B2: 3 | C2: Email intro
A3: 2 | B3: 1 | C3: Call + voicemail
A4: 3 | B4: 3 | C4: Email re: savings
A5: 4 | B5: 3 | C5: LinkedIn
A6: 5 | B6: 3 | C6: Call
A7: 6 | B7: 3 | C7: Email case study
A8: 7 | B8: 3 | C8: Call
A9: 8 | B9: 3 | C9: Breakup email

Sheet READ ME
B2: CoreTrust Master Members with Fit v3 scoring
B3: Every CoreTrust member on one row, scored by Fit v3 so the rep can tell at a glance whether an account is worth qualifying. This build is seeded with representative real accounts. Re-drop the two source files and run fitv3_engine.py to score all 25,461 members into this same structure.
B5: The Fit v3 score
B6: • Fit v3 = 30% freight opportunity + 30% CoreTrust engrainment + 15% freight intensity + 15% contact actionability + 10% relationship warmth.
B7: • Freight opportunity and engrainment carry the most weight, a member with a real freight budget that already buys through CoreTrust is the easiest logistics cross sell.
B8: • Actionability answers whether we can actually reach the account. Verified logistics-titled email 100, generic 75, hand-researched name 40, nothing 0.
B9: • Tiers: A 70+, B 55+, C 40+, D below. A means a real freight budget and a proven CoreTrust buying habit.
B11: How the rep uses it
B12: • Sort by Fit_v3_Score. Work tier A and B with a contact. C is nurture. D is not worth qualifying yet.
B13: • Service_Fit tells you what to pitch. Green columns are computed, do not overwrite them.
B15: The Touchpoints tab
B16: • Mirrors the master for accounts in active outreach. Tracks every email, call, and LinkedIn touch.
... B22: • Excluded: non-US members, K-12 districts, PE-firm and VC records, and transportation companies.
